LICENSE
README.md
setup.py
smatchpp/__init__.py
smatchpp/__main__.py
smatchpp/align.py
smatchpp/bindings.py
smatchpp/data_helpers.py
smatchpp/eval_statistics.py
smatchpp/graph_transforms.py
smatchpp/interfaces.py
smatchpp/log_helper.py
smatchpp/model_factory.py
smatchpp/preprocess.py
smatchpp/score.py
smatchpp/solvers.py
smatchpp/subgraph_extraction.py
smatchpp/util.py
smatchpp.egg-info/PKG-INFO
smatchpp.egg-info/SOURCES.txt
smatchpp.egg-info/dependency_links.txt
smatchpp.egg-info/requires.txt
smatchpp.egg-info/top_level.txt
smatchpp/formalism/amr/tools.py
smatchpp/formalism/amr/resource/concept_groups.json
smatchpp/formalism/amr/resource/graph_aspects.json
smatchpp/formalism/amr/resource/propbank-amr-frames-arg-descr.txt
smatchpp/formalism/amr/resource/reify_table.txt
smatchpp/formalism/generic/tools.py