Metadata-Version: 2.1
Name: smatchpp
Version: 1.8.0
Summary: A Python package for graph processing
Home-page: https://github.com/flipz357/smatchpp
Author: Juri Opitz
Author-email: opitz.sci@gmail.com
License: GPLv3
Platform: UNKNOWN
Classifier: License :: OSI Approved :: GNU General Public License v3 (GPLv3)
Requires-Python: >=3.5
License-File: LICENSE
